deriva_dev/__init__.py
deriva_dev-0.0.1.dist-info/METADATA
deriva_dev-0.0.1.dist-info/WHEEL
deriva_dev-0.0.1.dist-info/licenses/LICENSE
deriva_dev-0.0.1.dist-info/RECORD
