Metadata-Version: 2.4
Name: deriva-dev
Version: 0.0.1
Summary: Development tools for Deriva
Project-URL: Homepage, https://github.com/deriva-dev
Author: deriva-dev
License-Expression: MIT
License-File: LICENSE
Classifier: Development Status :: 1 - Planning
Classifier: License :: OSI Approved :: MIT License
Classifier: Programming Language :: Python :: 3
Requires-Python: >=3.8
